<?xml version="1.0" encoding="UTF-8"?>
<databaseChangeLog
        xmlns="http://www.liquibase.org/xml/ns/dbchangelog"
        xmlns:xsi="http://www.w3.org/2001/XMLSchema-instance"
        xsi:schemaLocation="http://www.liquibase.org/xml/ns/dbchangelog
         https://www.liquibase.org/xml/ns/dbchangelog/dbchangelog-4.5.xsd"
        logicalFilePath="db/changelog.xml">
    <changeSet id="003-insert-data-admin" author="jouk">
        <insert tableName="users" schemaName="ylab_schema">
            <column name="id" valueNumeric="3"/>
            <column name="email" value="admin@example.com"/>
            <column name="name" value="Admin"/>
            <column name="password" value="adminpass123"/>
            <column name="role" value="ADMIN"/>
        </insert>
    </changeSet>
</databaseChangeLog>
